README.md
setup.py
httpsec/__init__.py
httpsec/__version__.py
httpsec/api.py
httpsec/connection.py
httpsec/connectionpool.py
httpsec/httpclient.py
httpsec/poolmanager.py
httpsec/response.py
httpsec/sessions.py
httpsec/url.py
httpsec/utils.py
httpsec.egg-info/PKG-INFO
httpsec.egg-info/SOURCES.txt
httpsec.egg-info/dependency_links.txt
httpsec.egg-info/not-zip-safe
httpsec.egg-info/requires.txt
httpsec.egg-info/top_level.txt