Metadata-Version: 2.1
Name: httpsec
Version: 0.3.0
Summary: Python HTTP for Cybersecurity Practitioner
Home-page: https://github.com/tongchengbin/httpsec
Author: unknown
Author-email: unknown@outlook.com
License: Apache 2.0
Project-URL: Documentation, https://github.com/tongchengbin/httpsec
Project-URL: Source, https://github.com/tongchengbin/httpsec
Platform: UNKNOWN
Classifier: Development Status :: 5 - Production/Stable
Classifier: Environment :: Web Environment
Classifier: Intended Audience :: Developers
Classifier: License :: OSI Approved :: Apache Software License
Classifier: Natural Language :: English
Classifier: Operating System :: OS Independent
Classifier: Programming Language :: Python
Classifier: Programming Language :: Python :: 3
Classifier: Programming Language :: Python :: 3.7
Classifier: Programming Language :: Python :: 3.8
Classifier: Programming Language :: Python :: 3.9
Classifier: Programming Language :: Python :: 3.10
Classifier: Programming Language :: Python :: 3.11
Classifier: Programming Language :: Python :: 3 :: Only
Classifier: Programming Language :: Python :: Implementation :: CPython
Classifier: Programming Language :: Python :: Implementation :: PyPy
Classifier: Topic :: Internet :: WWW/HTTP
Classifier: Topic :: Software Development :: Libraries
Requires-Python: >=3.7, <4
Provides-Extra: security
Provides-Extra: socks
Provides-Extra: use_chardet_on_py3
